{
  "commit": "975515f100fba28ddb1c8ac8e9966b4a4d01625f",
  "readme": "/_/azure-rest-api-specs/specification/appconfiguration/resource-manager/readme.md",
  "tag": "package-2019-10-01",
  "use": "@microsoft.azure/autorest.go@2.1.187",
  "repository_url": "https://github.com/Azure/azure-rest-api-specs.git",
  "autorest_command": "autorest --use=@microsoft.azure/autorest.go@2.1.187 --tag=package-2019-10-01 --go-sdk-folder=/_/azure-sdk-for-go --go --verbose --use-onever --version=2.0.4421 --go.license-header=MICROSOFT_MIT_NO_VERSION /_/azure-rest-api-specs/specification/appconfiguration/resource-manager/readme.md",
  "additional_properties": {
    "additional_options": "--go --verbose --use-onever --version=2.0.4421 --go.license-header=MICROSOFT_MIT_NO_VERSION"
  }
}